strataregula_doe_runner/__init__.py
strataregula_doe_runner/cli.py
strataregula_doe_runner/plugin.py
strataregula_doe_runner/adapters/__init__.py
strataregula_doe_runner/adapters/base.py
strataregula_doe_runner/adapters/dummy.py
strataregula_doe_runner/adapters/shell.py
strataregula_doe_runner/core/__init__.py
strataregula_doe_runner/core/cache.py
strataregula_doe_runner/core/config.py
strataregula_doe_runner/core/executor.py
strataregula_doe_runner/core/runner.py
strataregula_doe_runner/core/validator.py
strataregula_doe_runner/io/__init__.py
strataregula_doe_runner/io/csv_handler.py
strataregula_doe_runner/io/metrics.py
strataregula_doe_runner/io/runlog.py
strataregula_doe_runner-0.3.0.dist-info/METADATA
strataregula_doe_runner-0.3.0.dist-info/WHEEL
strataregula_doe_runner-0.3.0.dist-info/entry_points.txt
strataregula_doe_runner-0.3.0.dist-info/licenses/LICENSE
strataregula_doe_runner-0.3.0.dist-info/RECORD
