Metadata-Version: 2.4
Name: strataregula-doe-runner
Version: 0.3.0
Summary: Batch experiment orchestrator for Strataregula ecosystem
Project-URL: Homepage, https://github.com/strataregula/strataregula-doe-runner
Project-URL: Documentation, https://strataregula-doe-runner.readthedocs.io/
Project-URL: Repository, https://github.com/strataregula/strataregula-doe-runner.git
Project-URL: Issues, https://github.com/strataregula/strataregula-doe-runner/issues
Author-email: Strataregula Team <team@strataregula.com>
License-Expression: Apache-2.0
License-File: LICENSE
Keywords: batch,csv,experiment,metrics,orchestrator,strataregula
Classifier: Development Status :: 4 - Beta
Classifier: Intended Audience :: Developers
Classifier: Intended Audience :: Science/Research
Classifier: Programming Language :: Python :: 3
Classifier: Programming Language :: Python :: 3.8
Classifier: Programming Language :: Python :: 3.9
Classifier: Programming Language :: Python :: 3.10
Classifier: Programming Language :: Python :: 3.11
Classifier: Programming Language :: Python :: 3.12
Classifier: Topic :: Scientific/Engineering
Classifier: Topic :: Software Development :: Libraries :: Python Modules
Classifier: Topic :: System :: Systems Administration
Requires-Python: >=3.8
Requires-Dist: click>=8.0.0
Requires-Dist: pydantic>=1.8.0
Requires-Dist: python-dateutil>=2.8.0
Requires-Dist: pyyaml>=6.0
Provides-Extra: dev
Requires-Dist: bandit>=1.8.0; extra == 'dev'
Requires-Dist: mypy>=0.910; extra == 'dev'
Requires-Dist: pytest-cov>=2.10.0; extra == 'dev'
Requires-Dist: pytest>=6.0.0; extra == 'dev'
Requires-Dist: ruff>=0.1.0; extra == 'dev'
Provides-Extra: docs
Requires-Dist: myst-parser>=0.15.0; extra == 'docs'
Requires-Dist: sphinx-rtd-theme>=0.5.0; extra == 'docs'
Requires-Dist: sphinx>=4.0.0; extra == 'docs'
Provides-Extra: simroute
Requires-Dist: numpy>=1.20.0; extra == 'simroute'
Requires-Dist: pandas>=1.3.0; extra == 'simroute'
Provides-Extra: test
Requires-Dist: pytest-cov>=2.10.0; extra == 'test'
Requires-Dist: pytest>=6.0.0; extra == 'test'
